paranoid/__init__.py
paranoid/__main__.py
paranoid/_version.py
paranoid/decorators.py
paranoid/exceptions.py
paranoid/ignore.py
paranoid/settings.py
paranoid/testfunctions.py
paranoid/utils.py
paranoid/types/__init__.py
paranoid/types/base.py
paranoid/types/collections.py
paranoid/types/numeric.py
paranoid/types/string.py
paranoid_scientist-0.2.2.dist-info/LICENSE.txt
paranoid_scientist-0.2.2.dist-info/METADATA
paranoid_scientist-0.2.2.dist-info/WHEEL
paranoid_scientist-0.2.2.dist-info/top_level.txt
paranoid_scientist-0.2.2.dist-info/RECORD
