Metadata-Version: 2.1
Name: paranoid-scientist
Version: 0.2.2
Summary: Runtime verification and automated testing for scientific code
Home-page: https://github.com/mwshinn/paranoidscientist
Author: Max Shinn
Author-email: maxwell.shinn@yale.edu
Maintainer: Max Shinn
Maintainer-email: maxwell.shinn@yale.edu
License: MIT
Platform: UNKNOWN
Classifier: Development Status :: 5 - Production/Stable
Classifier: Intended Audience :: Developers
Classifier: Intended Audience :: Science/Research
Classifier: License :: OSI Approved :: MIT License
Classifier: Programming Language :: Python :: 3
Classifier: Topic :: Education :: Testing
Classifier: Topic :: Scientific/Engineering
Classifier: Topic :: Software Development :: Quality Assurance
Classifier: Topic :: Software Development :: Testing
Requires-Python: >=3.5
